itakello_logging/__init__.py
itakello_logging/core.py
itakello_logging/filters/__init__.py
itakello_logging/filters/custom_exclude.py
itakello_logging/filters/ignore_root.py
itakello_logging/formatters/__init__.py
itakello_logging/formatters/console.py
itakello_logging/loggers/__init__.py
itakello_logging/loggers/custom_logger.py
itakello_logging-0.2.1.7.dist-info/LICENSE
itakello_logging-0.2.1.7.dist-info/METADATA
itakello_logging-0.2.1.7.dist-info/WHEEL
itakello_logging-0.2.1.7.dist-info/top_level.txt
itakello_logging-0.2.1.7.dist-info/RECORD
