Metadata-Version: 2.1
Name: itakello_logging
Version: 0.2.1.7
Summary: A custom logging library by Itakello
Home-page: https://github.com/Itakello/itakello_logging
Author: Itakello
Author-email: maxste000@gmail.com
Requires-Python: >=3.10
License-File: LICENSE
Provides-Extra: dev
Requires-Dist: types-setuptools ; extra == 'dev'
Requires-Dist: mypy ; extra == 'dev'
Requires-Dist: pytest ; extra == 'dev'
